decorations/__init__.py
decorations/__main__.py
decorations-0.0.0.dist-info/LICENSE.txt
decorations-0.0.0.dist-info/METADATA
decorations-0.0.0.dist-info/WHEEL
decorations-0.0.0.dist-info/top_level.txt
decorations-0.0.0.dist-info/RECORD
