Metadata-Version: 2.1
Name: decorations
Version: 0.0.0
Summary: decorations
Author-email: Johannes <johannes-programming@mailfence.com>
License: The MIT License (MIT)
Project-URL: Download, https://pypi.org/project/decorations/#files
Project-URL: Source, https://github.com/johannes-programming/decorations
Classifier: License :: OSI Approved :: MIT License
Classifier: Programming Language :: Python
Classifier: Programming Language :: Python :: 3
Classifier: Programming Language :: Python :: 3 :: Only
Requires-Python: >=3.12.4
License-File: LICENSE.txt
